Metadata-Version: 2.1
Name: harrywang-greeter
Version: 0.0.1
Summary: A minimal PyPI package
Home-page: https://github.com/harrywang/greeter-python
Author: Harry Wang
Author-email: harryjwang@gmail.com
License: MIT
Classifier: License :: OSI Approved :: MIT License
Classifier: Programming Language :: Python
Classifier: Programming Language :: Python :: 3
License-File: LICENSE
